{
    "AdditionalCurrency": 0,
    "AdditionalShards": 0,
    "AuraCurseBonus": "regeneration",
    "AuraCurseBonusValue": 1,
    "CardClass": "Healer",
    "CustomDescription": "",
    "DamageFlatBonus": "None",
    "DamageFlatBonusValue": 0,
    "EnergyBegin": 0,
    "HealQuantity": 0,
    "Icon": "regeneration",
    "IconTextValue": "+1",
    "ID": "healer6e",
    "Level": 6,
    "MainPerk": false,
    "MaxHealth": 0,
    "ObeliskPerk": false,
    "ResistModified": "None",
    "ResistModifiedValue": 0,
    "Row": 5,
    "SpeedQuantity": 0
}