{
    "AdditionalCurrency": 0,
    "AdditionalShards": 0,
    "AuraCurseBonus": "spark",
    "AuraCurseBonusValue": 1,
    "CardClass": "Mage",
    "CustomDescription": "",
    "DamageFlatBonus": "None",
    "DamageFlatBonusValue": 0,
    "EnergyBegin": 0,
    "HealQuantity": 0,
    "Icon": "spark",
    "IconTextValue": "+1",
    "ID": "mage13",
    "Level": 13,
    "MainPerk": false,
    "MaxHealth": 0,
    "ObeliskPerk": true,
    "ResistModified": "None",
    "ResistModifiedValue": 0,
    "Row": 1,
    "SpeedQuantity": 0
}