{
    "DefaultPercentEpic": 0.0,
    "DefaultPercentMythic": 0.0,
    "DefaultPercentRare": 30.0,
    "DefaultPercentUncommon": 70.0,
    "GoldQuantity": 50,
    "ID": "sahtifishingshop",
    "LootItemTable": [
        "{\n    \"LootCard\": \"fishingrod\",\n    \"LootPercent\": 100.0,\n    \"LootRarity\": \"Common\",\n    \"LootType\": \"None\"\n}",
        "{\n    \"LootCard\": \"bucket\",\n    \"LootPercent\": 100.0,\n    \"LootRarity\": \"Common\",\n    \"LootType\": \"None\"\n}",
        "{\n    \"LootCard\": \"fishbonesoup\",\n    \"LootPercent\": 100.0,\n    \"LootRarity\": \"Common\",\n    \"LootType\": \"None\"\n}",
        "{\n    \"LootCard\": \"fishcage\",\n    \"LootPercent\": 100.0,\n    \"LootRarity\": \"Common\",\n    \"LootType\": \"None\"\n}",
        "{\n    \"LootCard\": \"sahtipendant\",\n    \"LootPercent\": 100.0,\n    \"LootRarity\": \"Common\",\n    \"LootType\": \"None\"\n}",
        "{\n    \"LootCard\": \"salt\",\n    \"LootPercent\": 100.0,\n    \"LootRarity\": \"Common\",\n    \"LootType\": \"None\"\n}"
    ],
    "NumItems": 8,
    "ShadyModel": "farmerb",
    "ShadyScaleX": 1.0,
    "ShadyScaleY": 1.0,
    "ShadyOffsetX": 0.0,
    "ShadyOffsetY": 0.0
}