{
    "CombatPercent": 0,
    "Description": "",
    "DisableCorruption": false,
    "DisableRandom": false,
    "EventPercent": 0,
    "ExistsPercent": 100,
    "ExistsSku": "",
    "GoToTown": false,
    "NodeBackgroundImg": "",
    "NodeCombat": [
        "challenge_2a"
    ],
    "NodeCombatTier": "T2",
    "NodeEvent": [],
    "NodeEventPercent": [],
    "NodeEventPriority": [],
    "NodeEventTier": "T0",
    "NodeGround": "None",
    "NodeId": "ol2_8",
    "NodeName": "",
    "NodeRequirement": "",
    "NodesConnected": [
        "ol2_12"
    ],
    "NodesConnectedRequirement": [],
    "NodeZone": "Ol2",
    "TravelDestination": false,
    "VisibleIfNotRequirement": false,
    "medsPosX": -3.5134029388427736,
    "medsPosY": 0.615970253944397,
    "SourceNodeName": ""
}