{
    "CombatPercent": 0,
    "Description": "",
    "DisableCorruption": false,
    "DisableRandom": false,
    "EventPercent": 0,
    "ExistsPercent": 100,
    "ExistsSku": "",
    "GoToTown": false,
    "NodeBackgroundImg": "",
    "NodeCombat": [
        "culmin_26"
    ],
    "NodeCombatTier": "T4",
    "NodeEvent": [],
    "NodeEventPercent": [],
    "NodeEventPriority": [],
    "NodeEventTier": "T0",
    "NodeGround": "None",
    "NodeId": "ulmin_26",
    "NodeName": "Pyramid Entrance",
    "NodeRequirement": "",
    "NodesConnected": [
        "ulmin_31"
    ],
    "NodesConnectedRequirement": [],
    "NodeZone": "Ulminin",
    "TravelDestination": false,
    "VisibleIfNotRequirement": false,
    "medsPosX": 3.111999988555908,
    "medsPosY": -3.6040000915527345,
    "SourceNodeName": ""
}