{
    "CinematicData": "",
    "CombatBackground": "Velkarath_Lava2",
    "CombatEffect": [],
    "CombatID": "cvelka_4",
    "CombatMusic": "Valley of the Sun - 320bit",
    "CombatTier": "T3",
    "Description": "sectarios",
    "EventData": "",
    "EventRequirementData": "",
    "HealHeroes": false,
    "NPCList": [
        "firebrander_a",
        "fireimp",
        "evoker_a",
        "evoker_a"
    ],
    "NPCRemoveInMadness0Index": 3,
    "ThermometerTierData": "T2",
    "IsRift": false
}