{
    "CinematicData": "",
    "CombatBackground": "Senenthia_LobosNoche",
    "CombatEffect": [
        "{\n    \"AuraCurse\": \"slow\",\n    \"AuraCurseCharges\": 3,\n    \"AuraCurseTarget\": \"Monsters\"\n}",
        "{\n    \"AuraCurse\": \"weak\",\n    \"AuraCurseCharges\": 1,\n    \"AuraCurseTarget\": \"Monsters\"\n}"
    ],
    "CombatID": "esen_27d",
    "CombatMusic": "9_Alexander Nakarada - Dawn",
    "CombatTier": "T2",
    "Description": "yogger event 1",
    "EventData": "e_sen27_c",
    "EventRequirementData": "",
    "HealHeroes": false,
    "NPCList": [
        "",
        "",
        "yogger"
    ],
    "NPCRemoveInMadness0Index": -1,
    "ThermometerTierData": "T3",
    "IsRift": false
}