{
    "CombatPercent": 0,
    "Description": "",
    "DisableCorruption": false,
    "DisableRandom": false,
    "EventPercent": 0,
    "ExistsPercent": 100,
    "ExistsSku": "",
    "GoToTown": false,
    "NodeBackgroundImg": "",
    "NodeCombat": [],
    "NodeCombatTier": "T0",
    "NodeEvent": [],
    "NodeEventPercent": [],
    "NodeEventPriority": [],
    "NodeEventTier": "T0",
    "NodeGround": "None",
    "NodeId": "ol5_0",
    "NodeName": "",
    "NodeRequirement": "",
    "NodesConnected": [
        "ol5_1",
        "ol5_2",
        "ol5_3",
        "ol5_4"
    ],
    "NodesConnectedRequirement": [],
    "NodeZone": "Ol5",
    "TravelDestination": true,
    "VisibleIfNotRequirement": false,
    "medsPosX": 0.0,
    "medsPosY": 0.0,
    "SourceNodeName": "Obelisk Challenge"
}