{
    "AICards": [
        "{\n    \"AddCardRound\": 2,\n    \"AuraCurseCastIf\": \"\",\n    \"Card\": \"sharpenm\",\n    \"OnlyCastIf\": \"Always\",\n    \"PercentToCast\": 0.0,\n    \"Priority\": 0,\n    \"TargetCast\": \"Random\",\n    \"UnitsInDeck\": 1,\n    \"ValueCastIf\": 0.0\n}",
        "{\n    \"AddCardRound\": 0,\n    \"AuraCurseCastIf\": \"\",\n    \"Card\": \"aimedshotm\",\n    \"OnlyCastIf\": \"Always\",\n    \"PercentToCast\": 0.0,\n    \"Priority\": 2,\n    \"TargetCast\": \"Random\",\n    \"UnitsInDeck\": 1,\n    \"ValueCastIf\": 0.0\n}",
        "{\n    \"AddCardRound\": 0,\n    \"AuraCurseCastIf\": \"\",\n    \"Card\": \"crazylook\",\n    \"OnlyCastIf\": \"Always\",\n    \"PercentToCast\": 0.0,\n    \"Priority\": 1,\n    \"TargetCast\": \"Random\",\n    \"UnitsInDeck\": 1,\n    \"ValueCastIf\": 0.0\n}",
        "{\n    \"AddCardRound\": 0,\n    \"AuraCurseCastIf\": \"\",\n    \"Card\": \"fishbone\",\n    \"OnlyCastIf\": \"Always\",\n    \"PercentToCast\": 0.0,\n    \"Priority\": 5,\n    \"TargetCast\": \"Random\",\n    \"UnitsInDeck\": 1,\n    \"ValueCastIf\": 0.0\n}"
    ],
    "AuraCurseImmune": [],
    "BaseMonster": "",
    "BigModel": false,
    "CardsInHand": 2,
    "Description": "",
    "Difficulty": 5,
    "Energy": 10,
    "EnergyTurn": 0,
    "ExperienceReward": 45,
    "Female": false,
    "FinishCombatOnDead": false,
    "FluffOffsetX": -0.550000011920929,
    "FluffOffsetY": 2.9000000953674318,
    "GameObjectAnimated": "Archerfish",
    "GoldReward": 36,
    "HellModeMob": "",
    "HitSound": "",
    "HP": 95,
    "ID": "archerfish",
    "IsBoss": false,
    "IsNamed": false,
    "NgPlusMob": "archerfish_plus",
    "NPCName": "Archerfish",
    "PosBottom": 0.0,
    "PreferredPosition": "Back",
    "ResistBlunt": 16,
    "ResistCold": 32,
    "ResistFire": -8,
    "ResistHoly": 0,
    "ResistLightning": 12,
    "ResistMind": 0,
    "ResistPiercing": 21,
    "ResistShadow": 16,
    "ResistSlashing": 21,
    "ScriptableObjectName": "Archerfish",
    "Speed": 15,
    "Sprite": "",
    "SpritePortrait": "RangedFishportraitGrande",
    "SpriteSpeed": "RangedFishportrait",
    "TierMob": "T1",
    "TierReward": "4",
    "UpgradedMob": "archerfish_b",
    "GameObjectFlip": false,
    "GameObjectMakeBig": false,
    "GameObjectReplaceTexture": ""
}