{
    "AICards": [
        "{\n    \"AddCardRound\": 2,\n    \"AuraCurseCastIf\": \"\",\n    \"Card\": \"shatterma\",\n    \"OnlyCastIf\": \"Always\",\n    \"PercentToCast\": 0.0,\n    \"Priority\": 10,\n    \"StartsAtObeliskMadnessLevel\": 0,\n    \"StartsAtSingularityMadnessLevel\": 0,\n    \"SpecialSecondTargetID\": \"\",\n    \"SecondOnlyCastIf\": \"\",\n    \"SecondValueCastIf\": 0.0,\n    \"TargetCast\": \"Random\",\n    \"UnitsInDeck\": 1,\n    \"ValueCastIf\": 0.0\n}",
        "{\n    \"AddCardRound\": 4,\n    \"AuraCurseCastIf\": \"\",\n    \"Card\": \"shatterma\",\n    \"OnlyCastIf\": \"Always\",\n    \"PercentToCast\": 0.0,\n    \"Priority\": 10,\n    \"StartsAtObeliskMadnessLevel\": 0,\n    \"StartsAtSingularityMadnessLevel\": 0,\n    \"SpecialSecondTargetID\": \"\",\n    \"SecondOnlyCastIf\": \"\",\n    \"SecondValueCastIf\": 0.0,\n    \"TargetCast\": \"Random\",\n    \"UnitsInDeck\": 1,\n    \"ValueCastIf\": 0.0\n}",
        "{\n    \"AddCardRound\": 6,\n    \"AuraCurseCastIf\": \"\",\n    \"Card\": \"shatterma\",\n    \"OnlyCastIf\": \"Always\",\n    \"PercentToCast\": 0.0,\n    \"Priority\": 10,\n    \"StartsAtObeliskMadnessLevel\": 0,\n    \"StartsAtSingularityMadnessLevel\": 0,\n    \"SpecialSecondTargetID\": \"\",\n    \"SecondOnlyCastIf\": \"\",\n    \"SecondValueCastIf\": 0.0,\n    \"TargetCast\": \"Random\",\n    \"UnitsInDeck\": 1,\n    \"ValueCastIf\": 0.0\n}",
        "{\n    \"AddCardRound\": 8,\n    \"AuraCurseCastIf\": \"\",\n    \"Card\": \"shatterma\",\n    \"OnlyCastIf\": \"Always\",\n    \"PercentToCast\": 0.0,\n    \"Priority\": 10,\n    \"StartsAtObeliskMadnessLevel\": 0,\n    \"StartsAtSingularityMadnessLevel\": 0,\n    \"SpecialSecondTargetID\": \"\",\n    \"SecondOnlyCastIf\": \"\",\n    \"SecondValueCastIf\": 0.0,\n    \"TargetCast\": \"Random\",\n    \"UnitsInDeck\": 1,\n    \"ValueCastIf\": 0.0\n}",
        "{\n    \"AddCardRound\": 10,\n    \"AuraCurseCastIf\": \"\",\n    \"Card\": \"shatterma\",\n    \"OnlyCastIf\": \"Always\",\n    \"PercentToCast\": 0.0,\n    \"Priority\": 10,\n    \"StartsAtObeliskMadnessLevel\": 0,\n    \"StartsAtSingularityMadnessLevel\": 0,\n    \"SpecialSecondTargetID\": \"\",\n    \"SecondOnlyCastIf\": \"\",\n    \"SecondValueCastIf\": 0.0,\n    \"TargetCast\": \"Random\",\n    \"UnitsInDeck\": 1,\n    \"ValueCastIf\": 0.0\n}",
        "{\n    \"AddCardRound\": 0,\n    \"AuraCurseCastIf\": \"\",\n    \"Card\": \"repairarmorma\",\n    \"OnlyCastIf\": \"Always\",\n    \"PercentToCast\": 0.0,\n    \"Priority\": 1,\n    \"StartsAtObeliskMadnessLevel\": 0,\n    \"StartsAtSingularityMadnessLevel\": 0,\n    \"SpecialSecondTargetID\": \"\",\n    \"SecondOnlyCastIf\": \"\",\n    \"SecondValueCastIf\": 0.0,\n    \"TargetCast\": \"Random\",\n    \"UnitsInDeck\": 1,\n    \"ValueCastIf\": 0.0\n}",
        "{\n    \"AddCardRound\": 2,\n    \"AuraCurseCastIf\": \"\",\n    \"Card\": \"spectralscalesa\",\n    \"OnlyCastIf\": \"Always\",\n    \"PercentToCast\": 0.0,\n    \"Priority\": 2,\n    \"StartsAtObeliskMadnessLevel\": 0,\n    \"StartsAtSingularityMadnessLevel\": 0,\n    \"SpecialSecondTargetID\": \"\",\n    \"SecondOnlyCastIf\": \"\",\n    \"SecondValueCastIf\": 0.0,\n    \"TargetCast\": \"Random\",\n    \"UnitsInDeck\": 1,\n    \"ValueCastIf\": 0.0\n}",
        "{\n    \"AddCardRound\": 4,\n    \"AuraCurseCastIf\": \"\",\n    \"Card\": \"spectralscalesa\",\n    \"OnlyCastIf\": \"Always\",\n    \"PercentToCast\": 0.0,\n    \"Priority\": 2,\n    \"StartsAtObeliskMadnessLevel\": 0,\n    \"StartsAtSingularityMadnessLevel\": 0,\n    \"SpecialSecondTargetID\": \"\",\n    \"SecondOnlyCastIf\": \"\",\n    \"SecondValueCastIf\": 0.0,\n    \"TargetCast\": \"Random\",\n    \"UnitsInDeck\": 1,\n    \"ValueCastIf\": 0.0\n}",
        "{\n    \"AddCardRound\": 7,\n    \"AuraCurseCastIf\": \"\",\n    \"Card\": \"spectralscalesa\",\n    \"OnlyCastIf\": \"Always\",\n    \"PercentToCast\": 0.0,\n    \"Priority\": 2,\n    \"StartsAtObeliskMadnessLevel\": 0,\n    \"StartsAtSingularityMadnessLevel\": 0,\n    \"SpecialSecondTargetID\": \"\",\n    \"SecondOnlyCastIf\": \"\",\n    \"SecondValueCastIf\": 0.0,\n    \"TargetCast\": \"Random\",\n    \"UnitsInDeck\": 1,\n    \"ValueCastIf\": 0.0\n}",
        "{\n    \"AddCardRound\": 10,\n    \"AuraCurseCastIf\": \"\",\n    \"Card\": \"spectralscalesa\",\n    \"OnlyCastIf\": \"Always\",\n    \"PercentToCast\": 0.0,\n    \"Priority\": 2,\n    \"StartsAtObeliskMadnessLevel\": 0,\n    \"StartsAtSingularityMadnessLevel\": 0,\n    \"SpecialSecondTargetID\": \"\",\n    \"SecondOnlyCastIf\": \"\",\n    \"SecondValueCastIf\": 0.0,\n    \"TargetCast\": \"Random\",\n    \"UnitsInDeck\": 1,\n    \"ValueCastIf\": 0.0\n}",
        "{\n    \"AddCardRound\": 0,\n    \"AuraCurseCastIf\": \"\",\n    \"Card\": \"stompa\",\n    \"OnlyCastIf\": \"Always\",\n    \"PercentToCast\": 0.0,\n    \"Priority\": 3,\n    \"StartsAtObeliskMadnessLevel\": 0,\n    \"StartsAtSingularityMadnessLevel\": 0,\n    \"SpecialSecondTargetID\": \"\",\n    \"SecondOnlyCastIf\": \"\",\n    \"SecondValueCastIf\": 0.0,\n    \"TargetCast\": \"Random\",\n    \"UnitsInDeck\": 1,\n    \"ValueCastIf\": 0.0\n}",
        "{\n    \"AddCardRound\": 0,\n    \"AuraCurseCastIf\": \"\",\n    \"Card\": \"molebustera\",\n    \"OnlyCastIf\": \"Always\",\n    \"PercentToCast\": 0.0,\n    \"Priority\": 4,\n    \"StartsAtObeliskMadnessLevel\": 0,\n    \"StartsAtSingularityMadnessLevel\": 0,\n    \"SpecialSecondTargetID\": \"\",\n    \"SecondOnlyCastIf\": \"\",\n    \"SecondValueCastIf\": 0.0,\n    \"TargetCast\": \"Random\",\n    \"UnitsInDeck\": 1,\n    \"ValueCastIf\": 0.0\n}",
        "{\n    \"AddCardRound\": 1,\n    \"AuraCurseCastIf\": \"\",\n    \"Card\": \"earthquakea\",\n    \"OnlyCastIf\": \"Always\",\n    \"PercentToCast\": 0.0,\n    \"Priority\": 5,\n    \"StartsAtObeliskMadnessLevel\": 0,\n    \"StartsAtSingularityMadnessLevel\": 0,\n    \"SpecialSecondTargetID\": \"\",\n    \"SecondOnlyCastIf\": \"\",\n    \"SecondValueCastIf\": 0.0,\n    \"TargetCast\": \"Random\",\n    \"UnitsInDeck\": 1,\n    \"ValueCastIf\": 0.0\n}",
        "{\n    \"AddCardRound\": 3,\n    \"AuraCurseCastIf\": \"\",\n    \"Card\": \"aftershocka\",\n    \"OnlyCastIf\": \"Always\",\n    \"PercentToCast\": 0.0,\n    \"Priority\": 5,\n    \"StartsAtObeliskMadnessLevel\": 0,\n    \"StartsAtSingularityMadnessLevel\": 0,\n    \"SpecialSecondTargetID\": \"\",\n    \"SecondOnlyCastIf\": \"\",\n    \"SecondValueCastIf\": 0.0,\n    \"TargetCast\": \"Random\",\n    \"UnitsInDeck\": 1,\n    \"ValueCastIf\": 0.0\n}",
        "{\n    \"AddCardRound\": 1,\n    \"AuraCurseCastIf\": \"\",\n    \"Card\": \"coldweaponsa\",\n    \"OnlyCastIf\": \"Always\",\n    \"PercentToCast\": 0.0,\n    \"Priority\": 0,\n    \"StartsAtObeliskMadnessLevel\": 0,\n    \"StartsAtSingularityMadnessLevel\": 0,\n    \"SpecialSecondTargetID\": \"\",\n    \"SecondOnlyCastIf\": \"\",\n    \"SecondValueCastIf\": 0.0,\n    \"TargetCast\": \"Random\",\n    \"UnitsInDeck\": 1,\n    \"ValueCastIf\": 0.0\n}",
        "{\n    \"AddCardRound\": 5,\n    \"AuraCurseCastIf\": \"\",\n    \"Card\": \"coldweaponsa\",\n    \"OnlyCastIf\": \"Always\",\n    \"PercentToCast\": 0.0,\n    \"Priority\": 0,\n    \"StartsAtObeliskMadnessLevel\": 0,\n    \"StartsAtSingularityMadnessLevel\": 0,\n    \"SpecialSecondTargetID\": \"\",\n    \"SecondOnlyCastIf\": \"\",\n    \"SecondValueCastIf\": 0.0,\n    \"TargetCast\": \"Random\",\n    \"UnitsInDeck\": 1,\n    \"ValueCastIf\": 0.0\n}",
        "{\n    \"AddCardRound\": 7,\n    \"AuraCurseCastIf\": \"\",\n    \"Card\": \"coldweaponsa\",\n    \"OnlyCastIf\": \"Always\",\n    \"PercentToCast\": 0.0,\n    \"Priority\": 0,\n    \"StartsAtObeliskMadnessLevel\": 0,\n    \"StartsAtSingularityMadnessLevel\": 0,\n    \"SpecialSecondTargetID\": \"\",\n    \"SecondOnlyCastIf\": \"\",\n    \"SecondValueCastIf\": 0.0,\n    \"TargetCast\": \"Random\",\n    \"UnitsInDeck\": 1,\n    \"ValueCastIf\": 0.0\n}",
        "{\n    \"AddCardRound\": 2,\n    \"AuraCurseCastIf\": \"\",\n    \"Card\": \"flashfreezemm\",\n    \"OnlyCastIf\": \"Always\",\n    \"PercentToCast\": 0.0,\n    \"Priority\": 6,\n    \"StartsAtObeliskMadnessLevel\": 0,\n    \"StartsAtSingularityMadnessLevel\": 0,\n    \"SpecialSecondTargetID\": \"\",\n    \"SecondOnlyCastIf\": \"\",\n    \"SecondValueCastIf\": 0.0,\n    \"TargetCast\": \"Random\",\n    \"UnitsInDeck\": 1,\n    \"ValueCastIf\": 0.0\n}"
    ],
    "AuraCurseImmune": [
        "paralyze"
    ],
    "BaseMonster": "",
    "BigModel": true,
    "CardsInHand": 4,
    "Description": "",
    "Difficulty": 16,
    "Energy": 10,
    "EnergyTurn": 0,
    "ExperienceReward": 150,
    "Female": false,
    "FinishCombatOnDead": true,
    "FluffOffsetX": -0.10000000149011612,
    "FluffOffsetY": 4.199999809265137,
    "GameObjectAnimated": "dragon3",
    "GameObjectAnimatedAlternate": "",
    "GoldReward": 150,
    "HellModeMob": "",
    "HitSound": "",
    "HP": 898,
    "OnlyKillBossWhenHpZero": false,
    "ID": "graendor_o",
    "IsBoss": true,
    "IsNamed": true,
    "NgPlusMob": "graendor_o_plus",
    "NPCName": "Graendor",
    "PosBottom": 0.0,
    "PreferredPosition": "Back",
    "ResistBlunt": 36,
    "ResistCold": 50,
    "ResistFire": 0,
    "ResistHoly": 8,
    "ResistLightning": 0,
    "ResistMind": 28,
    "ResistPiercing": 28,
    "ResistShadow": 36,
    "ResistSlashing": 36,
    "ScriptableObjectName": "Graendor",
    "Speed": 15,
    "Sprite": "",
    "SpritePortrait": "DragonGeneralPortraitGrande",
    "SpriteSpeed": "DragonGeneralPortraitPequeño",
    "SpriteSpeedAlternate": "",
    "SpritePortraitAlternate": "",
    "TierMob": "T2",
    "TierReward": "19",
    "UpgradedMob": "",
    "GameObjectFlip": false,
    "GameObjectMakeBig": false,
    "GameObjectReplaceTexture": ""
}