{
    "AICards": [
        "{\n    \"AddCardRound\": 0,\n    \"AuraCurseCastIf\": \"\",\n    \"Card\": \"sacredbeamb\",\n    \"OnlyCastIf\": \"Always\",\n    \"PercentToCast\": 0.0,\n    \"Priority\": 1,\n    \"StartsAtObeliskMadnessLevel\": 0,\n    \"StartsAtSingularityMadnessLevel\": 0,\n    \"SpecialSecondTargetID\": \"\",\n    \"SecondOnlyCastIf\": \"\",\n    \"SecondValueCastIf\": 0.0,\n    \"TargetCast\": \"Random\",\n    \"UnitsInDeck\": 1,\n    \"ValueCastIf\": 0.0\n}",
        "{\n    \"AddCardRound\": 0,\n    \"AuraCurseCastIf\": \"\",\n    \"Card\": \"barriermb\",\n    \"OnlyCastIf\": \"Always\",\n    \"PercentToCast\": 0.0,\n    \"Priority\": 2,\n    \"StartsAtObeliskMadnessLevel\": 0,\n    \"StartsAtSingularityMadnessLevel\": 0,\n    \"SpecialSecondTargetID\": \"\",\n    \"SecondOnlyCastIf\": \"\",\n    \"SecondValueCastIf\": 0.0,\n    \"TargetCast\": \"Random\",\n    \"UnitsInDeck\": 1,\n    \"ValueCastIf\": 0.0\n}",
        "{\n    \"AddCardRound\": 2,\n    \"AuraCurseCastIf\": \"\",\n    \"Card\": \"holyrushb\",\n    \"OnlyCastIf\": \"Always\",\n    \"PercentToCast\": 0.0,\n    \"Priority\": 3,\n    \"StartsAtObeliskMadnessLevel\": 0,\n    \"StartsAtSingularityMadnessLevel\": 0,\n    \"SpecialSecondTargetID\": \"\",\n    \"SecondOnlyCastIf\": \"\",\n    \"SecondValueCastIf\": 0.0,\n    \"TargetCast\": \"Random\",\n    \"UnitsInDeck\": 1,\n    \"ValueCastIf\": 0.0\n}",
        "{\n    \"AddCardRound\": 4,\n    \"AuraCurseCastIf\": \"\",\n    \"Card\": \"holyrushb\",\n    \"OnlyCastIf\": \"Always\",\n    \"PercentToCast\": 0.0,\n    \"Priority\": 3,\n    \"StartsAtObeliskMadnessLevel\": 0,\n    \"StartsAtSingularityMadnessLevel\": 0,\n    \"SpecialSecondTargetID\": \"\",\n    \"SecondOnlyCastIf\": \"\",\n    \"SecondValueCastIf\": 0.0,\n    \"TargetCast\": \"Random\",\n    \"UnitsInDeck\": 1,\n    \"ValueCastIf\": 0.0\n}",
        "{\n    \"AddCardRound\": 6,\n    \"AuraCurseCastIf\": \"\",\n    \"Card\": \"holyrushb\",\n    \"OnlyCastIf\": \"Always\",\n    \"PercentToCast\": 0.0,\n    \"Priority\": 3,\n    \"StartsAtObeliskMadnessLevel\": 0,\n    \"StartsAtSingularityMadnessLevel\": 0,\n    \"SpecialSecondTargetID\": \"\",\n    \"SecondOnlyCastIf\": \"\",\n    \"SecondValueCastIf\": 0.0,\n    \"TargetCast\": \"Random\",\n    \"UnitsInDeck\": 1,\n    \"ValueCastIf\": 0.0\n}",
        "{\n    \"AddCardRound\": 8,\n    \"AuraCurseCastIf\": \"\",\n    \"Card\": \"holyrushb\",\n    \"OnlyCastIf\": \"Always\",\n    \"PercentToCast\": 0.0,\n    \"Priority\": 3,\n    \"StartsAtObeliskMadnessLevel\": 0,\n    \"StartsAtSingularityMadnessLevel\": 0,\n    \"SpecialSecondTargetID\": \"\",\n    \"SecondOnlyCastIf\": \"\",\n    \"SecondValueCastIf\": 0.0,\n    \"TargetCast\": \"Random\",\n    \"UnitsInDeck\": 1,\n    \"ValueCastIf\": 0.0\n}",
        "{\n    \"AddCardRound\": 2,\n    \"AuraCurseCastIf\": \"\",\n    \"Card\": \"divineshieldb\",\n    \"OnlyCastIf\": \"Always\",\n    \"PercentToCast\": 0.0,\n    \"Priority\": 0,\n    \"StartsAtObeliskMadnessLevel\": 0,\n    \"StartsAtSingularityMadnessLevel\": 0,\n    \"SpecialSecondTargetID\": \"\",\n    \"SecondOnlyCastIf\": \"\",\n    \"SecondValueCastIf\": 0.0,\n    \"TargetCast\": \"Random\",\n    \"UnitsInDeck\": 1,\n    \"ValueCastIf\": 0.0\n}",
        "{\n    \"AddCardRound\": 3,\n    \"AuraCurseCastIf\": \"\",\n    \"Card\": \"celestialtolla\",\n    \"OnlyCastIf\": \"Always\",\n    \"PercentToCast\": 0.0,\n    \"Priority\": 0,\n    \"StartsAtObeliskMadnessLevel\": 0,\n    \"StartsAtSingularityMadnessLevel\": 0,\n    \"SpecialSecondTargetID\": \"\",\n    \"SecondOnlyCastIf\": \"\",\n    \"SecondValueCastIf\": 0.0,\n    \"TargetCast\": \"Random\",\n    \"UnitsInDeck\": 1,\n    \"ValueCastIf\": 0.0\n}"
    ],
    "AuraCurseImmune": [],
    "BaseMonster": "",
    "BigModel": false,
    "CardsInHand": 2,
    "Description": "",
    "Difficulty": -1,
    "Energy": 10,
    "EnergyTurn": 0,
    "ExperienceReward": 58,
    "Female": false,
    "FinishCombatOnDead": false,
    "FluffOffsetX": -0.20000000298023225,
    "FluffOffsetY": 3.0,
    "GameObjectAnimated": "gyroorb",
    "GameObjectAnimatedAlternate": "",
    "GoldReward": 49,
    "HellModeMob": "",
    "HitSound": "",
    "HP": 275,
    "OnlyKillBossWhenHpZero": false,
    "ID": "gyroorb_plus_b",
    "IsBoss": false,
    "IsNamed": false,
    "NgPlusMob": "",
    "NPCName": "Gyro Orb",
    "PosBottom": 0.0,
    "PreferredPosition": "Front",
    "ResistBlunt": 36,
    "ResistCold": 20,
    "ResistFire": 42,
    "ResistHoly": 72,
    "ResistLightning": 42,
    "ResistMind": 20,
    "ResistPiercing": 58,
    "ResistShadow": 20,
    "ResistSlashing": 58,
    "ScriptableObjectName": "Gyro Orb",
    "Speed": 15,
    "Sprite": "",
    "SpritePortrait": "EscudoPiramidePortraitGrande",
    "SpriteSpeed": "EscudoPiramidePortrait",
    "SpriteSpeedAlternate": "",
    "SpritePortraitAlternate": "",
    "TierMob": "T2",
    "TierReward": "6",
    "UpgradedMob": "",
    "GameObjectFlip": false,
    "GameObjectMakeBig": false,
    "GameObjectReplaceTexture": ""
}