{
    "AICards": [
        "{\n    \"AddCardRound\": 0,\n    \"AuraCurseCastIf\": \"\",\n    \"Card\": \"furiousslashmb\",\n    \"OnlyCastIf\": \"Always\",\n    \"PercentToCast\": 0.0,\n    \"Priority\": 0,\n    \"TargetCast\": \"Random\",\n    \"UnitsInDeck\": 1,\n    \"ValueCastIf\": 0.0\n}",
        "{\n    \"AddCardRound\": 0,\n    \"AuraCurseCastIf\": \"\",\n    \"Card\": \"wildchargeb\",\n    \"OnlyCastIf\": \"Always\",\n    \"PercentToCast\": 0.0,\n    \"Priority\": 1,\n    \"TargetCast\": \"Random\",\n    \"UnitsInDeck\": 1,\n    \"ValueCastIf\": 0.0\n}",
        "{\n    \"AddCardRound\": 0,\n    \"AuraCurseCastIf\": \"\",\n    \"Card\": \"stompb\",\n    \"OnlyCastIf\": \"Always\",\n    \"PercentToCast\": 0.0,\n    \"Priority\": 3,\n    \"TargetCast\": \"Random\",\n    \"UnitsInDeck\": 1,\n    \"ValueCastIf\": 0.0\n}",
        "{\n    \"AddCardRound\": 0,\n    \"AuraCurseCastIf\": \"\",\n    \"Card\": \"indomitableb\",\n    \"OnlyCastIf\": \"Always\",\n    \"PercentToCast\": 0.0,\n    \"Priority\": 4,\n    \"TargetCast\": \"Random\",\n    \"UnitsInDeck\": 1,\n    \"ValueCastIf\": 0.0\n}",
        "{\n    \"AddCardRound\": 1,\n    \"AuraCurseCastIf\": \"\",\n    \"Card\": \"infuriatemb\",\n    \"OnlyCastIf\": \"Always\",\n    \"PercentToCast\": 0.0,\n    \"Priority\": 2,\n    \"TargetCast\": \"Random\",\n    \"UnitsInDeck\": 1,\n    \"ValueCastIf\": 0.0\n}",
        "{\n    \"AddCardRound\": 4,\n    \"AuraCurseCastIf\": \"\",\n    \"Card\": \"infuriatemb\",\n    \"OnlyCastIf\": \"Always\",\n    \"PercentToCast\": 0.0,\n    \"Priority\": 2,\n    \"TargetCast\": \"Random\",\n    \"UnitsInDeck\": 1,\n    \"ValueCastIf\": 0.0\n}",
        "{\n    \"AddCardRound\": 7,\n    \"AuraCurseCastIf\": \"\",\n    \"Card\": \"infuriatemb\",\n    \"OnlyCastIf\": \"Always\",\n    \"PercentToCast\": 0.0,\n    \"Priority\": 2,\n    \"TargetCast\": \"Random\",\n    \"UnitsInDeck\": 1,\n    \"ValueCastIf\": 0.0\n}",
        "{\n    \"AddCardRound\": 2,\n    \"AuraCurseCastIf\": \"\",\n    \"Card\": \"endurepainb\",\n    \"OnlyCastIf\": \"Always\",\n    \"PercentToCast\": 0.0,\n    \"Priority\": 8,\n    \"TargetCast\": \"Random\",\n    \"UnitsInDeck\": 1,\n    \"ValueCastIf\": 0.0\n}",
        "{\n    \"AddCardRound\": 4,\n    \"AuraCurseCastIf\": \"\",\n    \"Card\": \"endurepainb\",\n    \"OnlyCastIf\": \"Always\",\n    \"PercentToCast\": 0.0,\n    \"Priority\": 8,\n    \"TargetCast\": \"Random\",\n    \"UnitsInDeck\": 1,\n    \"ValueCastIf\": 0.0\n}",
        "{\n    \"AddCardRound\": 6,\n    \"AuraCurseCastIf\": \"\",\n    \"Card\": \"endurepainb\",\n    \"OnlyCastIf\": \"Always\",\n    \"PercentToCast\": 0.0,\n    \"Priority\": 7,\n    \"TargetCast\": \"Random\",\n    \"UnitsInDeck\": 1,\n    \"ValueCastIf\": 0.0\n}",
        "{\n    \"AddCardRound\": 8,\n    \"AuraCurseCastIf\": \"\",\n    \"Card\": \"endurepainb\",\n    \"OnlyCastIf\": \"Always\",\n    \"PercentToCast\": 0.0,\n    \"Priority\": 8,\n    \"TargetCast\": \"Random\",\n    \"UnitsInDeck\": 1,\n    \"ValueCastIf\": 0.0\n}",
        "{\n    \"AddCardRound\": 2,\n    \"AuraCurseCastIf\": \"\",\n    \"Card\": \"whirlwindmb\",\n    \"OnlyCastIf\": \"Always\",\n    \"PercentToCast\": 0.0,\n    \"Priority\": 5,\n    \"TargetCast\": \"Random\",\n    \"UnitsInDeck\": 1,\n    \"ValueCastIf\": 0.0\n}",
        "{\n    \"AddCardRound\": 4,\n    \"AuraCurseCastIf\": \"\",\n    \"Card\": \"whirlwindmb\",\n    \"OnlyCastIf\": \"Always\",\n    \"PercentToCast\": 0.0,\n    \"Priority\": 5,\n    \"TargetCast\": \"Random\",\n    \"UnitsInDeck\": 1,\n    \"ValueCastIf\": 0.0\n}",
        "{\n    \"AddCardRound\": 6,\n    \"AuraCurseCastIf\": \"\",\n    \"Card\": \"whirlwindmb\",\n    \"OnlyCastIf\": \"Always\",\n    \"PercentToCast\": 0.0,\n    \"Priority\": 5,\n    \"TargetCast\": \"Random\",\n    \"UnitsInDeck\": 1,\n    \"ValueCastIf\": 0.0\n}",
        "{\n    \"AddCardRound\": 9,\n    \"AuraCurseCastIf\": \"\",\n    \"Card\": \"whirlwindmb\",\n    \"OnlyCastIf\": \"Always\",\n    \"PercentToCast\": 0.0,\n    \"Priority\": 5,\n    \"TargetCast\": \"Random\",\n    \"UnitsInDeck\": 1,\n    \"ValueCastIf\": 0.0\n}",
        "{\n    \"AddCardRound\": 1,\n    \"AuraCurseCastIf\": \"\",\n    \"Card\": \"relentlessfury\",\n    \"OnlyCastIf\": \"Always\",\n    \"PercentToCast\": 0.0,\n    \"Priority\": 6,\n    \"TargetCast\": \"Random\",\n    \"UnitsInDeck\": 1,\n    \"ValueCastIf\": 0.0\n}"
    ],
    "AuraCurseImmune": [
        "paralyze"
    ],
    "BaseMonster": "",
    "BigModel": true,
    "CardsInHand": 4,
    "Description": "",
    "Difficulty": -1,
    "Energy": 10,
    "EnergyTurn": 0,
    "ExperienceReward": 150,
    "Female": false,
    "FinishCombatOnDead": true,
    "FluffOffsetX": -1.2999999523162842,
    "FluffOffsetY": 3.8499999046325685,
    "GameObjectAnimated": "minotaur",
    "GoldReward": 150,
    "HellModeMob": "",
    "HitSound": "",
    "HP": 1377,
    "ID": "minotaur_o_plus",
    "IsBoss": true,
    "IsNamed": true,
    "NgPlusMob": "",
    "NPCName": "Minotaur",
    "PosBottom": 0.0,
    "PreferredPosition": "Back",
    "ResistBlunt": 62,
    "ResistCold": 0,
    "ResistFire": 27,
    "ResistHoly": 6,
    "ResistLightning": 27,
    "ResistMind": 6,
    "ResistPiercing": 54,
    "ResistShadow": 42,
    "ResistSlashing": 48,
    "ScriptableObjectName": "Minotaur",
    "Speed": 17,
    "Sprite": "",
    "SpritePortrait": "minotaurSpeedBig",
    "SpriteSpeed": "minotaurSpeed",
    "TierMob": "T2",
    "TierReward": "19",
    "UpgradedMob": "",
    "GameObjectFlip": false,
    "GameObjectMakeBig": false,
    "GameObjectReplaceTexture": ""
}