{
    "AICards": [
        "{\n    \"AddCardRound\": 2,\n    \"AuraCurseCastIf\": \"\",\n    \"Card\": \"zealbarrier\",\n    \"OnlyCastIf\": \"Always\",\n    \"PercentToCast\": 0.0,\n    \"Priority\": 4,\n    \"StartsAtObeliskMadnessLevel\": 0,\n    \"StartsAtSingularityMadnessLevel\": 0,\n    \"SpecialSecondTargetID\": \"\",\n    \"SecondOnlyCastIf\": \"\",\n    \"SecondValueCastIf\": 0.0,\n    \"TargetCast\": \"Random\",\n    \"UnitsInDeck\": 1,\n    \"ValueCastIf\": 0.0\n}",
        "{\n    \"AddCardRound\": 1,\n    \"AuraCurseCastIf\": \"\",\n    \"Card\": \"holynovam\",\n    \"OnlyCastIf\": \"Always\",\n    \"PercentToCast\": 0.0,\n    \"Priority\": 2,\n    \"StartsAtObeliskMadnessLevel\": 0,\n    \"StartsAtSingularityMadnessLevel\": 0,\n    \"SpecialSecondTargetID\": \"\",\n    \"SecondOnlyCastIf\": \"\",\n    \"SecondValueCastIf\": 0.0,\n    \"TargetCast\": \"Random\",\n    \"UnitsInDeck\": 1,\n    \"ValueCastIf\": 0.0\n}",
        "{\n    \"AddCardRound\": 1,\n    \"AuraCurseCastIf\": \"\",\n    \"Card\": \"zealousprayer\",\n    \"OnlyCastIf\": \"Always\",\n    \"PercentToCast\": 0.0,\n    \"Priority\": 0,\n    \"StartsAtObeliskMadnessLevel\": 0,\n    \"StartsAtSingularityMadnessLevel\": 0,\n    \"SpecialSecondTargetID\": \"\",\n    \"SecondOnlyCastIf\": \"\",\n    \"SecondValueCastIf\": 0.0,\n    \"TargetCast\": \"Random\",\n    \"UnitsInDeck\": 1,\n    \"ValueCastIf\": 0.0\n}",
        "{\n    \"AddCardRound\": 2,\n    \"AuraCurseCastIf\": \"\",\n    \"Card\": \"ardentchampion\",\n    \"OnlyCastIf\": \"Always\",\n    \"PercentToCast\": 0.0,\n    \"Priority\": 1,\n    \"StartsAtObeliskMadnessLevel\": 0,\n    \"StartsAtSingularityMadnessLevel\": 0,\n    \"SpecialSecondTargetID\": \"\",\n    \"SecondOnlyCastIf\": \"\",\n    \"SecondValueCastIf\": 0.0,\n    \"TargetCast\": \"Random\",\n    \"UnitsInDeck\": 1,\n    \"ValueCastIf\": 0.0\n}",
        "{\n    \"AddCardRound\": 0,\n    \"AuraCurseCastIf\": \"\",\n    \"Card\": \"sacredboltm\",\n    \"OnlyCastIf\": \"Always\",\n    \"PercentToCast\": 0.0,\n    \"Priority\": 3,\n    \"StartsAtObeliskMadnessLevel\": 0,\n    \"StartsAtSingularityMadnessLevel\": 0,\n    \"SpecialSecondTargetID\": \"\",\n    \"SecondOnlyCastIf\": \"\",\n    \"SecondValueCastIf\": 0.0,\n    \"TargetCast\": \"Random\",\n    \"UnitsInDeck\": 1,\n    \"ValueCastIf\": 0.0\n}"
    ],
    "AuraCurseImmune": [],
    "BaseMonster": "",
    "BigModel": false,
    "CardsInHand": 2,
    "Description": "",
    "Difficulty": 9,
    "Energy": 10,
    "EnergyTurn": 0,
    "ExperienceReward": 55,
    "Female": false,
    "FinishCombatOnDead": false,
    "FluffOffsetX": -0.05000000074505806,
    "FluffOffsetY": 3.5999999046325685,
    "GameObjectAnimated": "priestess",
    "GameObjectAnimatedAlternate": "",
    "GoldReward": 46,
    "HellModeMob": "",
    "HitSound": "",
    "HP": 116,
    "OnlyKillBossWhenHpZero": false,
    "ID": "priestess",
    "IsBoss": false,
    "IsNamed": false,
    "NgPlusMob": "priestess_plus",
    "NPCName": "Priestess",
    "PosBottom": 0.0,
    "PreferredPosition": "Back",
    "ResistBlunt": 18,
    "ResistCold": 18,
    "ResistFire": 38,
    "ResistHoly": 52,
    "ResistLightning": 22,
    "ResistMind": 38,
    "ResistPiercing": -10,
    "ResistShadow": 12,
    "ResistSlashing": -10,
    "ScriptableObjectName": "Priestess",
    "Speed": 10,
    "Sprite": "",
    "SpritePortrait": "PanteraSacerdotisaPortraitGrande",
    "SpriteSpeed": "PanteraSacerdotisaPortrait",
    "SpriteSpeedAlternate": "",
    "SpritePortraitAlternate": "",
    "TierMob": "T1",
    "TierReward": "5",
    "UpgradedMob": "priestess_b",
    "GameObjectFlip": false,
    "GameObjectMakeBig": false,
    "GameObjectReplaceTexture": ""
}